azure/mgmt/cloudhealth/__init__.py
azure/mgmt/cloudhealth/_client.py
azure/mgmt/cloudhealth/_configuration.py
azure/mgmt/cloudhealth/_patch.py
azure/mgmt/cloudhealth/_version.py
azure/mgmt/cloudhealth/py.typed
azure/mgmt/cloudhealth/_utils/__init__.py
azure/mgmt/cloudhealth/_utils/model_base.py
azure/mgmt/cloudhealth/_utils/serialization.py
azure/mgmt/cloudhealth/aio/__init__.py
azure/mgmt/cloudhealth/aio/_client.py
azure/mgmt/cloudhealth/aio/_configuration.py
azure/mgmt/cloudhealth/aio/_patch.py
azure/mgmt/cloudhealth/aio/operations/__init__.py
azure/mgmt/cloudhealth/aio/operations/_operations.py
azure/mgmt/cloudhealth/aio/operations/_patch.py
azure/mgmt/cloudhealth/models/__init__.py
azure/mgmt/cloudhealth/models/_enums.py
azure/mgmt/cloudhealth/models/_models.py
azure/mgmt/cloudhealth/models/_patch.py
azure/mgmt/cloudhealth/operations/__init__.py
azure/mgmt/cloudhealth/operations/_operations.py
azure/mgmt/cloudhealth/operations/_patch.py
azure_mgmt_cloudhealth-1.0.0b1.dist-info/LICENSE
azure_mgmt_cloudhealth-1.0.0b1.dist-info/METADATA
azure_mgmt_cloudhealth-1.0.0b1.dist-info/WHEEL
azure_mgmt_cloudhealth-1.0.0b1.dist-info/top_level.txt
azure_mgmt_cloudhealth-1.0.0b1.dist-info/RECORD
